imltk/__init__.py
imltk-0.1.0.dist-info/LICENSE
imltk-0.1.0.dist-info/METADATA
imltk-0.1.0.dist-info/WHEEL
imltk-0.1.0.dist-info/top_level.txt
imltk-0.1.0.dist-info/RECORD
