Metadata-Version: 2.1
Name: imltk
Version: 0.1.0
Summary: Interpretable Machine Learning Toolkit
Home-page: https://github.com/blueloveTH/imltk
Author: blueloveTH
Author-email: blueloveTH@foxmail.com
License: UNKNOWN
Platform: UNKNOWN
Classifier: Programming Language :: Python :: 3
Classifier: License :: OSI Approved :: MIT License
Classifier: Operating System :: OS Independent
Requires-Python: >=3.6
Requires-Dist: pandas
